momosolaris_mcp_demo/__init__.py
momosolaris_mcp_demo-0.1.0.dist-info/WHEEL
momosolaris_mcp_demo-0.1.0.dist-info/entry_points.txt
momosolaris_mcp_demo-0.1.0.dist-info/METADATA
momosolaris_mcp_demo-0.1.0.dist-info/RECORD
