Metadata-Version: 2.3
Name: momosolaris-mcp-demo
Version: 0.1.0
Summary: Add your description here
Author: momo
Author-email: momo <momosunshine@gmail.com>
Requires-Dist: mcp[cli]>=1.13.1
Requires-Python: >=3.13
